m_lang_m-0.0.1.dist-info/licenses/LICENSE
mlangm/__init__.py
m_lang_m-0.0.1.dist-info/METADATA
m_lang_m-0.0.1.dist-info/WHEEL
m_lang_m-0.0.1.dist-info/top_level.txt
m_lang_m-0.0.1.dist-info/RECORD
