Metadata-Version: 2.4
Name: m-lang-m
Version: 0.0.1
Summary: Mini localization manager for Python using JSON/YAML files
Author-email: dusska <officialalexprofile@gmail.com>
License: MIT License
Project-URL: GitHub, https://github.com/poopscoin/mlangm
Keywords: localization,i18n,translation,python,json,yaml,language
Classifier: License :: OSI Approved :: MIT License
Classifier: Operating System :: OS Independent
Classifier: Topic :: Software Development :: Localization
Classifier: Programming Language :: Python :: 3.6
Classifier: Programming Language :: Python :: 3.7
Classifier: Programming Language :: Python :: 3.8
Classifier: Programming Language :: Python :: 3.9
Classifier: Programming Language :: Python :: 3.10
Classifier: Programming Language :: Python :: 3.11
Classifier: Programming Language :: Python :: 3.12
Classifier: Programming Language :: Python :: 3.13
Requires-Python: >=3.6
License-File: LICENSE
Requires-Dist: pyyaml>=6.0.2
Dynamic: license-file
